setup.py
pytorch_extras.egg-info/PKG-INFO
pytorch_extras.egg-info/SOURCES.txt
pytorch_extras.egg-info/dependency_links.txt
pytorch_extras.egg-info/top_level.txt
test/test_extras.py
torch_extras/__init__.py
torch_extras/extras.py