Metadata-Version: 1.0
Name: pytorch-extras
Version: 0.1.2
Summary: A handful of extensions to the pytorch library.
Home-page: http://github.com/mrdrozdov/pytorch-extras
Author: Andrew Drozdov
Author-email: andrew@mrdrozdov.com
License: MIT
Platform: UNKNOWN
